<?xml version="1.0" encoding="UTF-8"?>
<Command Name="DeleteDrWebClassic2" xmlns:xsi="http://www.w3.org/2001/XMLSchema-instance" xsi:noNamespaceSchemaLocation="Command.xsd">
	<Description>Service</Description>
	<Author Name="YAI" Date="2016-03-10+09:50"/>
	<Request Template="&#60;?xml version=&#34;1.0&#34; encoding=&#34;utf-8&#34;?&#62;
&#60;billing version=&#34;1.0&#34;&#62;
&#60;customer&#62;{0}&#60;/customer&#62;
&#60;service&#62;FR11809&#60;/service&#62;	
&#60;/billing&#62;">
	<Item Name="msisdn" Type="Wellknown" />
	</Request>
	<ErrorsList CodePage="ascii" >
			<Error Name="&#60;code&#62;33&#60;/code&#62;" Value="SUCCESS"/>
	</ErrorsList>
</Command>
