<BusinessProcessData name="Assign Public Wi-Fi Services">
  <businessprocess>
    <scenario>
      <objectlist>
        <object name="AddService" class="FORIS.ServiceProvisioning.BPM.BPMProcessingUnit" assembly="FORIS.SPA.BPMProcessingUnit.dll" />
      </objectlist>
      <automat>
        <node name="AssignServiceOnFINPlatform" object="AddService">
          <parameterslist>
            <param name="operation" value="AssignServiceOnFINPlatform" />
          </parameterslist>
          <resultlist>
            <result value="" node="AddFR12402onQP" />
          </resultlist>
        </node>
        <node name="AddFR12402onQP" object="AddService">
          <parameterslist>
            <param name="operation" value="AddFR12402onQP" />
          </parameterslist>
          <resultlist>
            <result value="" node="" />
          </resultlist>
        </node>
      </automat>
    </scenario>
  </businessprocess>
</BusinessProcessData>