<?xml version="1.0" encoding="UTF-8"?>
<Configuration>
  <serviceInstances>
    <serviceInstance hardwareID="SM:SMS">
      <scenarioSource type="FORIS.ServiceProvisioning.ServiceActivator.ScenarioSource.FileScenarioSource, FORIS.SPA.ServiceActivator.Core">
        <fileScenarioSource dir="..\SPA.SA\SPA.SA.SMSC\Scenarios"/>
      </scenarioSource>
      <socketList poolSize="10" autoconnect="1" maxConnections="10" minConnections="10" averageTime="300" deltaAverageTime="4000" maxCommandsPerPeriod="600" periodDuration="10" reconfigurationTimeout="0">
        <socket type="FORIS.ServiceProvisioning.Communication.Script.ManagedScriptSocket, FORIS.SPA.Communication">
          <config workingmode="wmPermanentEmulation">
            <socket type="FORIS.ServiceProvisioning.Communication.HttpSocket, FORIS.SPA.Communication">
              <config>
                <ParametersList>
                  <Parameter Key="Host" Value="10.160.32.108"/>
                  <Parameter Key="Port" Value="80"/>
                  <Parameter Key="Url" Value="smsc_subs_profile_ctrl/subs_ctrl.php?"/>
                  <Parameter Key="MethodName" Value="GET"/>
                  <Parameter Key="Method" Value="GET"/>
                  <Parameter Key="UserName" Value=""/>
                  <Parameter Key="UserPwd" Value=""/>
                  <Parameter Key="ContentType" Value="text/xml"/>
                </ParametersList>
              </config>
            </socket>
            <Emulation Success="..\SPA.SA\SPA.SA.SMSC\Emulation\printout.success.txt" Failure="..\SPA.SA\SPA.SA.SMSC\Emulation\printout.failure.txt" RandomizePrintout="false" OverwriteCommandPrintout="true"  Lifetime="00:00:00.00"/>
            <Timers IdleTimeout="10"/>
            <PredefinedScripts Login="Login" Command="Command" Idle="" Logoff=""/>
            <ScriptsList/>
          </config>
        </socket>
      </socketList>
      <context>
        <object name="dictionary" type="FORIS.ServiceProvisioning.Dictionary.ServiceActivatorDictionary, FORIS.SPA.Dictionary">
          <config path="..\SPA.SA\SPA.SA.SMSC" xml="Dictionary.xml" lifetime="00:01:30"/>
        </object>
        <object name="repetitionTable" type="FORIS.ServiceProvisioning.MmlProcessing.SPF.RepetitionTable, FORIS.SPA.MmlProcessing">
          <fileTableSource path="..\SPA.SA\Misc" xml="RepetitionTable.xml"/>
        </object>
      </context>
    </serviceInstance>
  </serviceInstances>
</Configuration>
