<Command Name="SC.Delete_AuthIMSI">
   <Description>Удаление IMSI на AUC</Description>
   <Author Name="system" Date="2018-09-20+09:00" />
   <Request>
      <RequestTemplate>
         <![CDATA[Del Auth : IMSI=##imsi##;^M]]>
      </RequestTemplate>
      <Item Name="imsi" Type="Wellknown" />
   </Request>
   <ErrorsList CodePage="windows-1251">
      <Error Name="101040" Value="SUCCESS" />
      <!--ISDN is unavailable-->
      <Error Name="101030" Value="SUCCESS" />
      <!--IMSI does not exist-->
   </ErrorsList>
</Command>